{
  "pools": [
    {
      "rolls": 1,
      "entries": [
        {
          "type": "minecraft:item",
          "name": "minecraft:paper",
          "functions": [
            {
              "function": "minecraft:set_components",
              "components": {
                "minecraft:item_model": "minecraft:rib_armor_trim_smithing_template",
                "minecraft:custom_name": {
                  "text": "Spellcharge - 8",
                  "color": "dark_gray",
                  "bold": true,
                  "italic": false
                },
                "minecraft:lore": [
                  [
                    {
                      "text": "Midnight Domain",
                      "color": "dark_gray",
                      "bold": true,
                      "italic": false
                    },
                    {
                      "text": " | ",
                      "color": "dark_gray",
                      "bold": false
                    },
                    {
                      "text": "Level 8 Spell",
                      "color": "gray"
                    }
                  ],
                  {
                    "text": "Recall Cost: 1",
                    "color": "dark_gray",
                    "italic": false
                  },
                  {
                    "text": ""
                  },
                  {
                    "text": "When you take magic damage, place tokens equal to marked",
                    "color": "white",
                    "italic": false
                  },
                  {
                    "text": "Hit Points on this card (up to Spellcast trait).",
                    "color": "white",
                    "italic": false
                  },
                  [
                    {
                      "text": "Spend tokens on successful attacks to add a ",
                      "color": "white",
                      "italic": false
                    },
                    {
                      "text": "d6",
                      "color": "white",
                      "italic": false,
                      "bold": true
                    },
                    {
                      "text": " per token.",
                      "color": "white",
                      "italic": false
                    }
                  ]
                ]
              }
            }
          ]
        }
      ]
    }
  ]
}
